LICENSE
README.md
setup.py
feedbackcompany/__init__.py
feedbackcompany/api.py
feedbackcompany.egg-info/PKG-INFO
feedbackcompany.egg-info/SOURCES.txt
feedbackcompany.egg-info/dependency_links.txt
feedbackcompany.egg-info/top_level.txt