Metadata-Version: 2.1
Name: feedbackcompany
Version: 0.1.0
Summary: Feedback Company API client
Home-page: https://github.com/marcocox/feedbackcompany-python
Author: Marco Cox
Author-email: mail@marcocox.com
License: MIT
Keywords: feedbackcompany api client
Platform: UNKNOWN
Classifier: Intended Audience :: Developers
Classifier: License :: OSI Approved :: MIT License
Classifier: Programming Language :: Python :: 3.3
Classifier: Programming Language :: Python :: 3.4
Classifier: Programming Language :: Python :: 3.5
Classifier: Programming Language :: Python :: 3.6
Classifier: Programming Language :: Python :: 3.7
Classifier: Programming Language :: Python :: 3.8
Classifier: Programming Language :: Python :: 3.9
Requires: requests
License-File: LICENSE
